dbeval/EvalTool.py
dbeval/Plotting.py
dbeval/__init__.py
dbeval-0.0.7.dist-info/LICENSE
dbeval-0.0.7.dist-info/METADATA
dbeval-0.0.7.dist-info/WHEEL
dbeval-0.0.7.dist-info/top_level.txt
dbeval-0.0.7.dist-info/RECORD
