Metadata-Version: 2.1
Name: dbeval
Version: 0.0.7
Summary: Database Performance and Scalability Evaluation Helpers
Home-page: https://github.com/luisremis/scaling-fiesta
Author: Luis Remis
Author-email: luis@remis.io
License: Apache
Platform: UNKNOWN
Classifier: Programming Language :: Python :: 3
Classifier: License :: OSI Approved :: Apache Software License
Classifier: Operating System :: OS Independent
Requires-Python: >=2.6, !=3.0.*, !=3.1.*, !=3.2.*, <4
License-File: LICENSE
Requires-Dist: matplotlib
Requires-Dist: numpy
Requires-Dist: pandas
